drf_standardized_responses/__init__.py
drf_standardized_responses/apps.py
drf_standardized_responses/exceptions.py
drf_standardized_responses/pagination.py
drf_standardized_responses/renderers.py
drf_standardized_responses/responses.py
drf_standardized_responses-0.1.4.dist-info/METADATA
drf_standardized_responses-0.1.4.dist-info/WHEEL
drf_standardized_responses-0.1.4.dist-info/licenses/LICENSE
drf_standardized_responses-0.1.4.dist-info/RECORD
