Metadata-Version: 2.4
Name: drf-standardized-responses
Version: 0.1.4
Summary: A Django REST Framework utility for standardized API responses, pagination, and exception handling.
Project-URL: Homepage, https://github.com/Yosef-AlSabbah/drf-standardized-responses
Project-URL: Repository, https://github.com/Yosef-AlSabbah/drf-standardized-responses
Project-URL: Issues, https://github.com/Yosef-AlSabbah/drf-standardized-responses/issues
Project-URL: Changelog, https://github.com/Yosef-AlSabbah/drf-standardized-responses/blob/main/CHANGELOG.md
Author-email: "Yousef M. Y. Al Sabbah" <itzyousefalsabbah@gmail.com>
License: BSD-3-Clause
License-File: LICENSE
Classifier: Development Status :: 4 - Beta
Classifier: Environment :: Web Environment
Classifier: Framework :: Django
Classifier: Framework :: Django :: 3.2
Classifier: Framework :: Django :: 4.0
Classifier: Framework :: Django :: 4.1
Classifier: Framework :: Django :: 4.2
Classifier: Framework :: Django :: 5.0
Classifier: Intended Audience :: Developers
Classifier: License :: OSI Approved :: BSD License
Classifier: Operating System :: OS Independent
Classifier: Programming Language :: Python
Classifier: Programming Language :: Python :: 3
Classifier: Programming Language :: Python :: 3.8
Classifier: Programming Language :: Python :: 3.9
Classifier: Programming Language :: Python :: 3.10
Classifier: Programming Language :: Python :: 3.11
Classifier: Programming Language :: Python :: 3.12
Classifier: Programming Language :: Python :: 3.13
Classifier: Topic :: Internet :: WWW/HTTP
Classifier: Topic :: Software Development :: Libraries :: Python Modules
Requires-Python: >=3.8
Requires-Dist: django>=3.2
Requires-Dist: djangorestframework>=3.13
